[{"home_team":"Annan Athletic","away_team":"Peterhead","home_goals":1,"away_goals":2,"date":1501891200000},{"home_team":"Berwick","away_team":"Clyde","home_goals":3,"away_goals":1,"date":1501891200000},{"home_team":"Edinburgh City","away_team":"Montrose","home_goals":1,"away_goals":3,"date":1501891200000},{"home_team":"Elgin","away_team":"Cowdenbeath","home_goals":1,"away_goals":1,"date":1501891200000},{"home_team":"Stenhousemuir","away_team":"Stirling","home_goals":2,"away_goals":3,"date":1501891200000},{"home_team":"Clyde","away_team":"Annan Athletic","home_goals":2,"away_goals":1,"date":1502496000000},{"home_team":"Cowdenbeath","away_team":"Edinburgh City","home_goals":1,"away_goals":0,"date":1502496000000},{"home_team":"Montrose","away_team":"Stenhousemuir","home_goals":1,"away_goals":1,"date":1502496000000},{"home_team":"Peterhead","away_team":"Elgin","home_goals":3,"away_goals":0,"date":1502496000000},{"home_team":"Stirling","away_team":"Berwick","home_goals":4,"away_goals":0,"date":1502496000000},{"home_team":"Berwick","away_team":"Annan Athletic","home_goals":1,"away_goals":5,"date":1503100800000},{"home_team":"Elgin","away_team":"Clyde","home_goals":3,"away_goals":2,"date":1503100800000},{"home_team":"Montrose","away_team":"Cowdenbeath","home_goals":1,"away_goals":0,"date":1503100800000},{"home_team":"Stenhousemuir","away_team":"Peterhead","home_goals":3,"away_goals":1,"date":1503100800000},{"home_team":"Stirling","away_team":"Edinburgh City","home_goals":2,"away_goals":0,"date":1503100800000},{"home_team":"Annan Athletic","away_team":"Montrose","home_goals":0,"away_goals":1,"date":1503705600000},{"home_team":"Clyde","away_team":"Stenhousemuir","home_goals":1,"away_goals":1,"date":1503705600000},{"home_team":"Cowdenbeath","away_team":"Berwick","home_goals":0,"away_goals":1,"date":1503705600000},{"home_team":"Edinburgh City","away_team":"Elgin","home_goals":0,"away_goals":3,"date":1503705600000},{"home_team":"Peterhead","away_team":"Stirling","home_goals":2,"away_goals":4,"date":1503705600000},{"home_team":"Edinburgh City","away_team":"Berwick","home_goals":1,"away_goals":0,"date":1504915200000},{"home_team":"Elgin","away_team":"Annan Athletic","home_goals":0,"away_goals":1,"date":1504915200000},{"home_team":"Peterhead","away_team":"Montrose","home_goals":1,"away_goals":1,"date":1504915200000},{"home_team":"Stenhousemuir","away_team":"Cowdenbeath","home_goals":1,"away_goals":0,"date":1504915200000},{"home_team":"Stirling","away_team":"Clyde","home_goals":2,"away_goals":3,"date":1504915200000},{"home_team":"Annan Athletic","away_team":"Stenhousemuir","home_goals":1,"away_goals":1,"date":1505520000000},{"home_team":"Berwick","away_team":"Elgin","home_goals":3,"away_goals":2,"date":1505520000000},{"home_team":"Clyde","away_team":"Edinburgh City","home_goals":2,"away_goals":3,"date":1505520000000},{"home_team":"Cowdenbeath","away_team":"Peterhead","home_goals":0,"away_goals":4,"date":1505520000000},{"home_team":"Montrose","away_team":"Stirling","home_goals":1,"away_goals":3,"date":1505520000000},{"home_team":"Clyde","away_team":"Cowdenbeath","home_goals":1,"away_goals":1,"date":1506124800000},{"home_team":"Edinburgh City","away_team":"Peterhead","home_goals":0,"away_goals":3,"date":1506124800000},{"home_team":"Elgin","away_team":"Montrose","home_goals":3,"away_goals":0,"date":1506124800000},{"home_team":"Stenhousemuir","away_team":"Berwick","home_goals":3,"away_goals":0,"date":1506124800000},{"home_team":"Stirling","away_team":"Annan Athletic","home_goals":3,"away_goals":2,"date":1506124800000},{"home_team":"Annan Athletic","away_team":"Cowdenbeath","home_goals":1,"away_goals":0,"date":1506729600000},{"home_team":"Montrose","away_team":"Clyde","home_goals":3,"away_goals":2,"date":1506729600000},{"home_team":"Peterhead","away_team":"Berwick","home_goals":0,"away_goals":2,"date":1506729600000},{"home_team":"Stenhousemuir","away_team":"Edinburgh City","home_goals":3,"away_goals":0,"date":1506729600000},{"home_team":"Stirling","away_team":"Elgin","home_goals":2,"away_goals":2,"date":1506729600000},{"home_team":"Berwick","away_team":"Montrose","home_goals":0,"away_goals":1,"date":1508544000000},{"home_team":"Clyde","away_team":"Peterhead","home_goals":1,"away_goals":4,"date":1508544000000},{"home_team":"Cowdenbeath","away_team":"Stirling","home_goals":0,"away_goals":3,"date":1508544000000},{"home_team":"Edinburgh City","away_team":"Annan Athletic","home_goals":0,"away_goals":1,"date":1508544000000},{"home_team":"Elgin","away_team":"Stenhousemuir","home_goals":2,"away_goals":0,"date":1508544000000},{"home_team":"Berwick","away_team":"Cowdenbeath","home_goals":1,"away_goals":0,"date":1509148800000},{"home_team":"Clyde","away_team":"Elgin","home_goals":2,"away_goals":4,"date":1509148800000},{"home_team":"Montrose","away_team":"Edinburgh City","home_goals":1,"away_goals":0,"date":1509148800000},{"home_team":"Peterhead","away_team":"Annan Athletic","home_goals":1,"away_goals":0,"date":1509148800000},{"home_team":"Stirling","away_team":"Stenhousemuir","home_goals":1,"away_goals":2,"date":1509148800000},{"home_team":"Annan Athletic","away_team":"Berwick","home_goals":0,"away_goals":0,"date":1509753600000},{"home_team":"Cowdenbeath","away_team":"Montrose","home_goals":1,"away_goals":3,"date":1509753600000},{"home_team":"Edinburgh City","away_team":"Stirling","home_goals":1,"away_goals":2,"date":1509753600000},{"home_team":"Elgin","away_team":"Peterhead","home_goals":0,"away_goals":2,"date":1509753600000},{"home_team":"Stenhousemuir","away_team":"Clyde","home_goals":1,"away_goals":1,"date":1509753600000},{"home_team":"Berwick","away_team":"Edinburgh City","home_goals":1,"away_goals":1,"date":1510358400000},{"home_team":"Clyde","away_team":"Stirling","home_goals":1,"away_goals":1,"date":1510358400000},{"home_team":"Cowdenbeath","away_team":"Elgin","home_goals":1,"away_goals":3,"date":1510358400000},{"home_team":"Montrose","away_team":"Annan Athletic","home_goals":1,"away_goals":1,"date":1510358400000},{"home_team":"Peterhead","away_team":"Stenhousemuir","home_goals":2,"away_goals":3,"date":1510358400000},{"home_team":"Cowdenbeath","away_team":"Annan Athletic","home_goals":1,"away_goals":1,"date":1510963200000},{"home_team":"Annan Athletic","away_team":"Clyde","home_goals":0,"away_goals":0,"date":1511568000000},{"home_team":"Edinburgh City","away_team":"Cowdenbeath","home_goals":0,"away_goals":0,"date":1511568000000},{"home_team":"Elgin","away_team":"Berwick","home_goals":5,"away_goals":1,"date":1511568000000},{"home_team":"Stenhousemuir","away_team":"Montrose","home_goals":0,"away_goals":1,"date":1511568000000},{"home_team":"Annan Athletic","away_team":"Elgin","home_goals":2,"away_goals":0,"date":1512172800000},{"home_team":"Berwick","away_team":"Stirling","home_goals":1,"away_goals":0,"date":1512172800000},{"home_team":"Clyde","away_team":"Montrose","home_goals":0,"away_goals":0,"date":1512172800000},{"home_team":"Peterhead","away_team":"Edinburgh City","home_goals":3,"away_goals":0,"date":1512172800000},{"home_team":"Stirling","away_team":"Peterhead","home_goals":0,"away_goals":1,"date":1512432000000},{"home_team":"Elgin","away_team":"Edinburgh City","home_goals":1,"away_goals":1,"date":1512777600000},{"home_team":"Montrose","away_team":"Berwick","home_goals":3,"away_goals":0,"date":1512777600000},{"home_team":"Stenhousemuir","away_team":"Annan Athletic","home_goals":1,"away_goals":3,"date":1512777600000},{"home_team":"Annan Athletic","away_team":"Stirling","home_goals":1,"away_goals":1,"date":1513382400000},{"home_team":"Edinburgh City","away_team":"Stenhousemuir","home_goals":1,"away_goals":2,"date":1513382400000},{"home_team":"Montrose","away_team":"Elgin","home_goals":3,"away_goals":0,"date":1513382400000},{"home_team":"Cowdenbeath","away_team":"Stenhousemuir","home_goals":1,"away_goals":1,"date":1513641600000},{"home_team":"Annan Athletic","away_team":"Edinburgh City","home_goals":2,"away_goals":1,"date":1513987200000},{"home_team":"Clyde","away_team":"Berwick","home_goals":0,"away_goals":0,"date":1513987200000},{"home_team":"Peterhead","away_team":"Cowdenbeath","home_goals":3,"away_goals":2,"date":1513987200000},{"home_team":"Stenhousemuir","away_team":"Elgin","home_goals":4,"away_goals":1,"date":1513987200000},{"home_team":"Stirling","away_team":"Montrose","home_goals":0,"away_goals":1,"date":1513987200000},{"home_team":"Montrose","away_team":"Peterhead","home_goals":2,"away_goals":6,"date":1514592000000},{"home_team":"Clyde","away_team":"Annan Athletic","home_goals":0,"away_goals":0,"date":1514851200000},{"home_team":"Edinburgh City","away_team":"Berwick","home_goals":3,"away_goals":0,"date":1514851200000},{"home_team":"Montrose","away_team":"Cowdenbeath","home_goals":1,"away_goals":1,"date":1514851200000},{"home_team":"Peterhead","away_team":"Elgin","home_goals":7,"away_goals":0,"date":1514851200000},{"home_team":"Stenhousemuir","away_team":"Stirling","home_goals":2,"away_goals":1,"date":1514851200000},{"home_team":"Annan Athletic","away_team":"Montrose","home_goals":0,"away_goals":1,"date":1515196800000},{"home_team":"Cowdenbeath","away_team":"Edinburgh City","home_goals":0,"away_goals":2,"date":1515196800000},{"home_team":"Elgin","away_team":"Clyde","home_goals":2,"away_goals":1,"date":1515196800000},{"home_team":"Stenhousemuir","away_team":"Peterhead","home_goals":1,"away_goals":4,"date":1515196800000},{"home_team":"Stirling","away_team":"Berwick","home_goals":2,"away_goals":0,"date":1515196800000},{"home_team":"Berwick","away_team":"Annan Athletic","home_goals":0,"away_goals":2,"date":1515801600000},{"home_team":"Clyde","away_team":"Stenhousemuir","home_goals":0,"away_goals":3,"date":1515801600000},{"home_team":"Edinburgh City","away_team":"Montrose","home_goals":0,"away_goals":2,"date":1515801600000},{"home_team":"Elgin","away_team":"Cowdenbeath","home_goals":1,"away_goals":0,"date":1515801600000},{"home_team":"Peterhead","away_team":"Stirling","home_goals":4,"away_goals":3,"date":1515801600000},{"home_team":"Montrose","away_team":"Clyde","home_goals":1,"away_goals":3,"date":1516406400000},{"home_team":"Clyde","away_team":"Peterhead","home_goals":1,"away_goals":0,"date":1517011200000},{"home_team":"Cowdenbeath","away_team":"Berwick","home_goals":1,"away_goals":3,"date":1517011200000},{"home_team":"Edinburgh City","away_team":"Annan Athletic","home_goals":3,"away_goals":2,"date":1517011200000},{"home_team":"Elgin","away_team":"Stenhousemuir","home_goals":2,"away_goals":0,"date":1517011200000},{"home_team":"Montrose","away_team":"Stirling","home_goals":2,"away_goals":1,"date":1517011200000},{"home_team":"Berwick","away_team":"Peterhead","home_goals":2,"away_goals":3,"date":1517270400000},{"home_team":"Stirling","away_team":"Cowdenbeath","home_goals":1,"away_goals":0,"date":1517356800000},{"home_team":"Annan Athletic","away_team":"Cowdenbeath","home_goals":1,"away_goals":1,"date":1517616000000},{"home_team":"Clyde","away_team":"Edinburgh City","home_goals":3,"away_goals":2,"date":1517616000000},{"home_team":"Peterhead","away_team":"Montrose","home_goals":0,"away_goals":1,"date":1517616000000},{"home_team":"Stenhousemuir","away_team":"Berwick","home_goals":4,"away_goals":0,"date":1517616000000},{"home_team":"Stirling","away_team":"Elgin","home_goals":3,"away_goals":1,"date":1517616000000},{"home_team":"Berwick","away_team":"Clyde","home_goals":0,"away_goals":1,"date":1518220800000},{"home_team":"Cowdenbeath","away_team":"Stirling","home_goals":1,"away_goals":2,"date":1518220800000},{"home_team":"Edinburgh City","away_team":"Peterhead","home_goals":0,"away_goals":0,"date":1518220800000},{"home_team":"Elgin","away_team":"Annan Athletic","home_goals":2,"away_goals":1,"date":1518220800000},{"home_team":"Montrose","away_team":"Stenhousemuir","home_goals":1,"away_goals":0,"date":1518220800000},{"home_team":"Clyde","away_team":"Cowdenbeath","home_goals":2,"away_goals":0,"date":1518825600000},{"home_team":"Elgin","away_team":"Montrose","home_goals":2,"away_goals":2,"date":1518825600000},{"home_team":"Peterhead","away_team":"Berwick","home_goals":1,"away_goals":1,"date":1518825600000},{"home_team":"Stenhousemuir","away_team":"Edinburgh City","home_goals":1,"away_goals":0,"date":1518825600000},{"home_team":"Stirling","away_team":"Annan Athletic","home_goals":3,"away_goals":0,"date":1518825600000},{"home_team":"Annan Athletic","away_team":"Peterhead","home_goals":3,"away_goals":3,"date":1519084800000},{"home_team":"Annan Athletic","away_team":"Stenhousemuir","home_goals":2,"away_goals":0,"date":1519430400000},{"home_team":"Berwick","away_team":"Montrose","home_goals":2,"away_goals":2,"date":1519430400000},{"home_team":"Cowdenbeath","away_team":"Peterhead","home_goals":0,"away_goals":2,"date":1519430400000},{"home_team":"Edinburgh City","away_team":"Elgin","home_goals":4,"away_goals":0,"date":1519430400000},{"home_team":"Stirling","away_team":"Clyde","home_goals":2,"away_goals":1,"date":1519430400000},{"home_team":"Peterhead","away_team":"Clyde","home_goals":2,"away_goals":1,"date":1519689600000},{"home_team":"Annan Athletic","away_team":"Edinburgh City","home_goals":2,"away_goals":3,"date":1520640000000},{"home_team":"Elgin","away_team":"Berwick","home_goals":3,"away_goals":0,"date":1520640000000},{"home_team":"Stenhousemuir","away_team":"Clyde","home_goals":2,"away_goals":3,"date":1520640000000},{"home_team":"Stirling","away_team":"Peterhead","home_goals":0,"away_goals":1,"date":1520640000000},{"home_team":"Berwick","away_team":"Stirling","home_goals":0,"away_goals":1,"date":1520899200000},{"home_team":"Clyde","away_team":"Elgin","home_goals":1,"away_goals":0,"date":1520899200000},{"home_team":"Edinburgh City","away_team":"Cowdenbeath","home_goals":1,"away_goals":1,"date":1520899200000},{"home_team":"Montrose","away_team":"Annan Athletic","home_goals":2,"away_goals":1,"date":1520899200000},{"home_team":"Peterhead","away_team":"Stenhousemuir","home_goals":1,"away_goals":2,"date":1520899200000},{"home_team":"Annan Athletic","away_team":"Clyde","home_goals":1,"away_goals":1,"date":1521244800000},{"home_team":"Cowdenbeath","away_team":"Elgin","home_goals":3,"away_goals":1,"date":1521244800000},{"home_team":"Edinburgh City","away_team":"Stirling","home_goals":2,"away_goals":2,"date":1521244800000},{"home_team":"Montrose","away_team":"Peterhead","home_goals":3,"away_goals":2,"date":1521244800000},{"home_team":"Edinburgh City","away_team":"Clyde","home_goals":0,"away_goals":3,"date":1521504000000},{"home_team":"Elgin","away_team":"Stirling","home_goals":0,"away_goals":2,"date":1521504000000},{"home_team":"Stenhousemuir","away_team":"Cowdenbeath","home_goals":1,"away_goals":2,"date":1521504000000},{"home_team":"Berwick","away_team":"Edinburgh City","home_goals":1,"away_goals":1,"date":1521849600000},{"home_team":"Clyde","away_team":"Montrose","home_goals":3,"away_goals":0,"date":1521849600000},{"home_team":"Peterhead","away_team":"Annan Athletic","home_goals":1,"away_goals":0,"date":1521849600000},{"home_team":"Stenhousemuir","away_team":"Elgin","home_goals":0,"away_goals":2,"date":1521849600000},{"home_team":"Stirling","away_team":"Cowdenbeath","home_goals":2,"away_goals":2,"date":1521849600000},{"home_team":"Berwick","away_team":"Elgin","home_goals":2,"away_goals":2,"date":1522108800000},{"home_team":"Cowdenbeath","away_team":"Clyde","home_goals":0,"away_goals":3,"date":1522108800000},{"home_team":"Stirling","away_team":"Edinburgh City","home_goals":2,"away_goals":2,"date":1522108800000},{"home_team":"Annan Athletic","away_team":"Berwick","home_goals":0,"away_goals":0,"date":1522454400000},{"home_team":"Cowdenbeath","away_team":"Stenhousemuir","home_goals":1,"away_goals":1,"date":1522454400000},{"home_team":"Elgin","away_team":"Stirling","home_goals":3,"away_goals":0,"date":1522454400000},{"home_team":"Montrose","away_team":"Edinburgh City","home_goals":3,"away_goals":0,"date":1522454400000},{"home_team":"Peterhead","away_team":"Clyde","home_goals":3,"away_goals":0,"date":1522454400000},{"home_team":"Annan Athletic","away_team":"Elgin","home_goals":4,"away_goals":1,"date":1523059200000},{"home_team":"Berwick","away_team":"Peterhead","home_goals":1,"away_goals":3,"date":1523059200000},{"home_team":"Cowdenbeath","away_team":"Clyde","home_goals":1,"away_goals":0,"date":1523059200000},{"home_team":"Edinburgh City","away_team":"Stenhousemuir","home_goals":1,"away_goals":4,"date":1523059200000},{"home_team":"Stirling","away_team":"Montrose","home_goals":0,"away_goals":5,"date":1523059200000},{"home_team":"Cowdenbeath","away_team":"Montrose","home_goals":0,"away_goals":3,"date":1523318400000},{"home_team":"Clyde","away_team":"Stirling","home_goals":2,"away_goals":1,"date":1523664000000},{"home_team":"Elgin","away_team":"Edinburgh City","home_goals":1,"away_goals":1,"date":1523664000000},{"home_team":"Montrose","away_team":"Berwick","home_goals":1,"away_goals":0,"date":1523664000000},{"home_team":"Peterhead","away_team":"Cowdenbeath","home_goals":1,"away_goals":0,"date":1523664000000},{"home_team":"Stenhousemuir","away_team":"Annan Athletic","home_goals":3,"away_goals":2,"date":1523664000000},{"home_team":"Berwick","away_team":"Stenhousemuir","home_goals":0,"away_goals":0,"date":1523923200000},{"home_team":"Annan Athletic","away_team":"Stirling","home_goals":3,"away_goals":1,"date":1524268800000},{"home_team":"Berwick","away_team":"Cowdenbeath","home_goals":1,"away_goals":0,"date":1524268800000},{"home_team":"Edinburgh City","away_team":"Clyde","home_goals":1,"away_goals":3,"date":1524268800000},{"home_team":"Elgin","away_team":"Peterhead","home_goals":0,"away_goals":1,"date":1524268800000},{"home_team":"Stenhousemuir","away_team":"Montrose","home_goals":0,"away_goals":2,"date":1524268800000},{"home_team":"Berwick","away_team":"Stenhousemuir","home_goals":2,"away_goals":2,"date":1524528000000},{"home_team":"Clyde","away_team":"Berwick","home_goals":1,"away_goals":2,"date":1524873600000},{"home_team":"Cowdenbeath","away_team":"Annan Athletic","home_goals":0,"away_goals":2,"date":1524873600000},{"home_team":"Montrose","away_team":"Elgin","home_goals":1,"away_goals":1,"date":1524873600000},{"home_team":"Peterhead","away_team":"Edinburgh City","home_goals":2,"away_goals":1,"date":1524873600000},{"home_team":"Stirling","away_team":"Stenhousemuir","home_goals":1,"away_goals":1,"date":1524873600000}]